cfn_sync/__init__.py
cfn_sync/cloudformation.py
cfn_sync/py.typed
cfn_sync-0.0.11.dist-info/LICENSE
cfn_sync-0.0.11.dist-info/METADATA
cfn_sync-0.0.11.dist-info/WHEEL
cfn_sync-0.0.11.dist-info/entry_points.txt
cfn_sync-0.0.11.dist-info/top_level.txt
cfn_sync-0.0.11.dist-info/RECORD
