Metadata-Version: 2.1
Name: cfn-sync
Version: 0.0.11
Summary: Deploy CloudFormation stacks synchronously and watch the events
Home-page: https://github.com/samjarrett/cfn-sync
Author: Sam Jarrett
Author-email: sam@samjarrett.com.au
Classifier: License :: OSI Approved :: MIT License
Classifier: Programming Language :: Python
Classifier: Programming Language :: Python :: 3
Classifier: Programming Language :: Python :: 3.7
Classifier: Programming Language :: Python :: 3.8
Classifier: Programming Language :: Python :: 3.9
Classifier: Programming Language :: Python :: 3.10
Requires-Python: >=3.7
License-File: LICENSE
Requires-Dist: boto3 (>=1.12.0)
